lakshmi/__init__.py
lakshmi/analyze.py
lakshmi/assets.py
lakshmi/cache.py
lakshmi/constants.py
lakshmi/lak.py
lakshmi/lakshmi.py
lakshmi/performance.py
lakshmi/table.py
lakshmi/utils.py
lakshmi/data/Account.yaml
lakshmi/data/AssetClass.yaml
lakshmi/data/Checkpoint.yaml
lakshmi/data/EEBonds.yaml
lakshmi/data/IBonds.yaml
lakshmi/data/ManualAsset.yaml
lakshmi/data/TickerAsset.yaml
lakshmi/data/VanguardFund.yaml
lakshmi-3.0.2.dist-info/licenses/LICENSE
lakshmi-3.0.2.dist-info/METADATA
lakshmi-3.0.2.dist-info/WHEEL
lakshmi-3.0.2.dist-info/entry_points.txt
lakshmi-3.0.2.dist-info/top_level.txt
lakshmi-3.0.2.dist-info/RECORD
