Metadata-Version: 2.4
Name: lakshmi
Version: 3.0.2
Summary: Investing library and command-line interface inspired by the Bogleheads philosophy
Home-page: https://github.com/sarvjeets/lakshmi
Author: Sarvjeet Singh
Author-email: sarvjeet@gmail.com
License: MIT
Platform: any
Classifier: Development Status :: 5 - Production/Stable
Classifier: License :: OSI Approved :: MIT License
Classifier: Operating System :: OS Independent
Classifier: Programming Language :: Python :: 3
Requires-Python: >=3.7
License-File: LICENSE
Requires-Dist: click~=8.0
Requires-Dist: curl_cffi~=0.10
Requires-Dist: ibonds<2.0,>=1.0.2
Requires-Dist: numpy<3.0,>=1.22
Requires-Dist: pyxirr~=0.6
Requires-Dist: PyYAML<7.0,>=5.4
Requires-Dist: requests~=2.25
Requires-Dist: tabulate~=0.8
Requires-Dist: yfinance<0.3,>=0.2.38
Dynamic: author
Dynamic: author-email
Dynamic: classifier
Dynamic: description
Dynamic: description-content-type
Dynamic: home-page
Dynamic: license
Dynamic: license-file
Dynamic: platform
Dynamic: requires-dist
Dynamic: requires-python
Dynamic: summary
